LICENSE.md
MANIFEST.in
README.md
setup.py
tec/__init__.py
tec.ic.ia.pc1.g03.egg-info/PKG-INFO
tec.ic.ia.pc1.g03.egg-info/SOURCES.txt
tec.ic.ia.pc1.g03.egg-info/dependency_links.txt
tec.ic.ia.pc1.g03.egg-info/entry_points.txt
tec.ic.ia.pc1.g03.egg-info/requires.txt
tec.ic.ia.pc1.g03.egg-info/top_level.txt
tec/ic/__init__.py
tec/ic/ia/__init__.py
tec/ic/ia/pc1/__init__.py
tec/ic/ia/pc1/g03.py
tec/ic/ia/pc1/archivos/actas.csv
tec/ic/ia/pc1/archivos/ejemplo_de_salida.csv
tec/ic/ia/pc1/archivos/indicadores.csv
tec/ic/ia/pc1/modelo/__gen_muestras.py
tec/ic/ia/pc1/modelo/__gen_promedios_indicadores.py
tec/ic/ia/pc1/modelo/__init__.py
tec/ic/ia/pc1/modelo/gen_randoms.py
tec/ic/ia/pc1/modelo/manejo_archivos.py
tec/ic/ia/pc1/modelo/manejo_consultas.py
tec/ic/ia/pc1/modelo/manejo_muestras.py
tec/ic/ia/pc1/pruebas/__init__.py
tec/ic/ia/pc1/pruebas/test_eficiencia.py
tec/ic/ia/pc1/pruebas/test_g03.py
tec/ic/ia/pc1/pruebas/test_gen_randoms.py
tec/ic/ia/pc1/pruebas/test_manejo_archivos.py
tec/ic/ia/pc1/pruebas/test_manejo_consultas.py
tec/ic/ia/pc1/util/__init__.py
tec/ic/ia/pc1/util/fuentes.py
tec/ic/ia/pc1/util/timeit.py