Metadata-Version: 1.2
Name: tec.ic.ia.pc1.g03
Version: 1.1.5
Summary: Inteligencia Artificial: Proyecto Corto I
Home-page: https://github.com/bdinarte/SimuladorVotantes
Author: Julian Salinas, Brandon Dinarte, Armando López
Author-email: UNKNOWN
License: GNU General Public License v3.0
Download-URL: https://github.com/bdinarte/SimuladorVotantes/archive/v1.1.1.tar.gz
Keywords: tec,ic,ia,g03
Platform: UNKNOWN
Requires-Python: >=3
